klldv5.py
klld-5.0.1.dist-info/LICENSE
klld-5.0.1.dist-info/METADATA
klld-5.0.1.dist-info/WHEEL
klld-5.0.1.dist-info/top_level.txt
klld-5.0.1.dist-info/RECORD
