Metadata-Version: 2.1
Name: klld
Version: 5.0.1
Summary: klld@email.com
Home-page: UNKNOWN
Author: klld
License: UNKNOWN
Keywords: klldv5,fortnte,fortnite bot
Platform: UNKNOWN
Classifier: Programming Language :: Python :: 3
Classifier: License :: OSI Approved :: MIT License
Classifier: Operating System :: OS Independent
Requires-Python: >=3.6
Requires-Dist: crayons
Requires-Dist: PirxcyPinger
Requires-Dist: fortnitepyBenBotAsync
Requires-Dist: FortniteAPIAsync
Requires-Dist: sanic
Requires-Dist: aiohttp
Requires-Dist: uvloop
Requires-Dist: requests
